MANIFEST.in
README.rst
setup.py
autocython/__init__.py
autocython/__main__.py
autocython/__version__.py
autocython/autocython.py
autocython.egg-info/PKG-INFO
autocython.egg-info/SOURCES.txt
autocython.egg-info/dependency_links.txt
autocython.egg-info/requires.txt
autocython.egg-info/top_level.txt
example/example.py
example/hello_package/__init__.py
example/hello_package/hello_module.pyx
example/hello_package/setup.py